s1_noisefloor-0.1.1.dist-info/METADATA
s1_noisefloor-0.1.1.dist-info/WHEEL
s1_noisefloor.cpython-38-x86_64-linux-gnu.so
s1_noisefloor-0.1.1.dist-info/RECORD
