Metadata-Version: 2.1
Name: s1-noisefloor
Version: 0.1.1
Classifier: Programming Language :: Rust
Classifier: Topic :: Scientific/Engineering :: GIS
Project-Url: https://github.com/PeterQLee/sentinel1_denoise_rs/
Summary: Algorithms to remove noise floor intensity patterns that are prevelant in Sentinel-1 cross-polarized images in EW and IW modes
Home-Page: https://github.com/PeterQLee/sentinel1_denoise_rs/
Author: PeterQLee <leep1995@gmail.com>
Author-Email: PeterQLee <leep1995@gmail.com>
License: MIT
